ase_extension/__init__.py
ase_extension/_ext.cpython-312-darwin.so
ase_extension/_ext.pyi
ase_extension/tools/__init__.py
ase_extension/tools/packmol.py
ase_extension/constraints/bias.py
ase_extension/constraints/__init__.py
ase_extension/constraints/fix.py
ase_extension/constraints/confine.py
ase_extension/calculators/__init__.py
ase_extension/calculators/xtb.py
ase_extension/geometry/molecule.py
ase_extension/geometry/rmsd.py
ase_extension/geometry/__init__.py
ase_extension/geometry/chemical_bonding.py
ext/constraints/shake.rs
ext/constraints/mod.rs
ext/constraints/wall_potential.rs
ext/geometry/rmsd.rs
ext/geometry/mod.rs
ase_extension-0.5.0.dist-info/RECORD
ase_extension-0.5.0.dist-info/WHEEL
ase_extension-0.5.0.dist-info/top_level.txt
ase_extension-0.5.0.dist-info/METADATA
